{
  "subject": "History of Pakistan & India",
  "year": "2023",
  "questions": [
    {
      "question_number": "2",
      "question_text": "Write a detailed note on the public administration under Muslim rule in India.",
      "marks": 20
    },
    {
      "question_number": "3",
      "question_text": "Critically examine the origin and growth of the East India Company as an imperialist power in India.",
      "marks": 20
    },
    {
      "question_number": "4",
      "question_text": "Give an historical account of the growth of Hindu nationalism during 1858-1947.",
      "marks": 20
    },
    {
      "question_number": "5",
      "question_text": "Evaluate the causes and effects of the Khilafat Movement on the Muslim struggle for independence.",
      "marks": 20
    },
    {
      "question_number": "6",
      "question_text": "Discuss the outcomes of the three sessions of the Round Table Conference.",
      "marks": 20
    },
    {
      "question_number": "7",
      "question_text": "Critically evaluate the role of political parties in the separation of East Pakistan in 1971.",
      "marks": 20
    },
    {
      "question_number": "8a",
      "question_text": "Write a short note on Kargil War.",
      "marks": 10
    },
    {
      "question_number": "8b",
      "question_text": "Write a short note on 1984 Referendum.",
      "marks": 10
    },
    {
      "question_number": "8c",
      "question_text": "Write a short note on Allahabad Address 1930.",
      "marks": 10
    }
  ]
}